femtum_sdk/__init__.py
femtum_sdk/database/__init__.py
femtum_sdk/database/adapter/__init__.py
femtum_sdk/database/adapter/analysis_pandas_adapter.py
femtum_sdk/database/adapter/tags_adapter.py
femtum_sdk/database/database_sdk.py
femtum_sdk/database/function/__init__.py
femtum_sdk/database/function/event.py
femtum_sdk/database/grpc/attachment_pb2.py
femtum_sdk/database/grpc/attachment_pb2.pyi
femtum_sdk/database/grpc/attachment_pb2_grpc.py
femtum_sdk/database/grpc/circuit_pb2.py
femtum_sdk/database/grpc/circuit_pb2.pyi
femtum_sdk/database/grpc/circuit_pb2_grpc.py
femtum_sdk/database/grpc/component_path_pb2.py
femtum_sdk/database/grpc/component_path_pb2.pyi
femtum_sdk/database/grpc/component_path_pb2_grpc.py
femtum_sdk/database/grpc/die_pb2.py
femtum_sdk/database/grpc/die_pb2.pyi
femtum_sdk/database/grpc/die_pb2_grpc.py
femtum_sdk/database/grpc/femtum_sdk.pb
femtum_sdk/database/grpc/function_pb2.py
femtum_sdk/database/grpc/function_pb2.pyi
femtum_sdk/database/grpc/function_pb2_grpc.py
femtum_sdk/database/grpc/health_pb2.py
femtum_sdk/database/grpc/health_pb2.pyi
femtum_sdk/database/grpc/health_pb2_grpc.py
femtum_sdk/database/grpc/processed_circuit_pb2.py
femtum_sdk/database/grpc/processed_circuit_pb2.pyi
femtum_sdk/database/grpc/processed_circuit_pb2_grpc.py
femtum_sdk/database/grpc/result_pb2.py
femtum_sdk/database/grpc/result_pb2.pyi
femtum_sdk/database/grpc/result_pb2_grpc.py
femtum_sdk/database/grpc/reticle_pb2.py
femtum_sdk/database/grpc/reticle_pb2.pyi
femtum_sdk/database/grpc/reticle_pb2_grpc.py
femtum_sdk/database/grpc/spectrum_pb2.py
femtum_sdk/database/grpc/spectrum_pb2.pyi
femtum_sdk/database/grpc/spectrum_pb2_grpc.py
femtum_sdk/database/grpc/tag_pb2.py
femtum_sdk/database/grpc/tag_pb2.pyi
femtum_sdk/database/grpc/tag_pb2_grpc.py
femtum_sdk/database/grpc/wafer_pb2.py
femtum_sdk/database/grpc/wafer_pb2.pyi
femtum_sdk/database/grpc/wafer_pb2_grpc.py
femtum_sdk/database/trimming_sdk.py
femtum_sdk-0.16.10.dist-info/METADATA
femtum_sdk-0.16.10.dist-info/WHEEL
femtum_sdk-0.16.10.dist-info/entry_points.txt
femtum_sdk-0.16.10.dist-info/RECORD
