Metadata-Version: 2.3
Name: femtum-sdk
Version: 0.16.10
Summary: Femtum SDK
Author: Samuel
Author-email: smagny@femtum.com
Requires-Python: >=3.11,<4.0
Classifier: Programming Language :: Python :: 3
Classifier: Programming Language :: Python :: 3.11
Classifier: Programming Language :: Python :: 3.12
Classifier: Programming Language :: Python :: 3.13
Requires-Dist: grpcio (>=1.70.0,<2.0.0)
Requires-Dist: pandas (>=2.2.3,<3.0.0)
Requires-Dist: protobuf (>=5.29.4,<6.0.0)
